location_helpers/__init__.py
location_helpers/address_helpers.py
location_helpers/mapquest_helpers.py
location_helpers/tests/__init__.py
location_helpers/tests/test_address_helpers.py
location_helpers/tests/test_mapquest_helpers.py
ctodd_python_lib_location-1.0.0.dist-info/LICENSE
ctodd_python_lib_location-1.0.0.dist-info/METADATA
ctodd_python_lib_location-1.0.0.dist-info/WHEEL
ctodd_python_lib_location-1.0.0.dist-info/top_level.txt
ctodd_python_lib_location-1.0.0.dist-info/RECORD
