Metadata-Version: 2.1
Name: ctodd-python-lib-location
Version: 1.0.0
Summary: Python utilities used for interacting with Locations
Home-page: https://github.com/ChristopherHaydenTodd/ctodd-python-lib-location
Author: Christopher H. Todd
Author-email: Christopher.Hayden.Todd@gmail.com
License: MIT
Keywords: python,libraries,location,geocoding
Platform: UNKNOWN
Classifier: Development Status :: 5 - Production/Stable
Classifier: Intended Audience :: Developers
Classifier: Natural Language :: English
Classifier: Programming Language :: Python
Classifier: Programming Language :: Python :: 3
Classifier: Programming Language :: Python :: 3.6
Classifier: Programming Language :: Python :: 3.7
Classifier: Programming Language :: Python :: 3.8
Requires-Python: >3.6
Requires-Dist: street-address (==0.4.0)
Requires-Dist: requests (==2.22.0)
Requires-Dist: geocoder (==1.38.1)
Requires-Dist: usaddress (==0.5.10)
